<hadoopConfig>
    <archive>hadoop-2.2.0.tar.gz</archive>
    <javahome>/usr/lib/jvm/jre/</javahome>
    <instance>
        <name>hadoop220_nohb_nozk</name>
        <dataroot>/var/lib/hadoop/nozk/</dataroot>
        <namenodedatadirs>/var/lib/hadoop/hadoop220_nohb_nozk/</namenodedatadirs>
        <datanodedatadirs>/var/lib/hadoop/hadoop220_nohb_nozk/</datanodedatadirs>
        <security>
            <kmshost>node004</kmshost>
            <usessl>false</usessl>
            <sslonly>false</sslonly>
        </security>
        <namenode>
            <host>node001</host>
            <port>8020</port>
            <httpport>50070</httpport>
            <httpsport>50470</httpsport>
        </namenode>
        <secondarynamenode>
            <host>node002</host>
            <httpport>50090</httpport>
            <httpsport>50091</httpsport>
        </secondarynamenode>
        <datanodes>
            <hosts>node001..node003</hosts>
            <port>50010</port>
            <ipcport>50020</ipcport>
            <httpport>50075</httpport>
            <httpsport>50475</httpsport>
            <nodemanagerlocalizerport>8040</nodemanagerlocalizerport>
            <nodemanagerwebappport>8042</nodemanagerwebappport>
            <nodemanagerwebapphttpsport>8044</nodemanagerwebapphttpsport>
            <nodemanagershuffleport>8091</nodemanagershuffleport>
        </datanodes>
        <yarnserver>
            <host>node003</host>
            <port>8032</port>
            <schedulerport>8030</schedulerport>
            <webappport>8088</webappport>
            <webapphttpsport>8090</webapphttpsport>
            <rtport>8031</rtport>
            <adminport>8033</adminport>
            <historyport>10020</historyport>
            <historywebappport>19888</historywebappport>
            <historywebapphttpsport>19890</historywebapphttpsport>
            <timelineport>10021</timelineport>
            <timelinewebappport>8188</timelinewebappport>
            <timelinewebapphttpsport>8190</timelinewebapphttpsport>
        </yarnserver>
    </instance>
</hadoopConfig>
